cs_bahtml/__init__.py
cs_bahtml/cs_bahtml.py
cs_bahtml/filtering.py
cs_bahtml/gospa.py
cs_bahtml/parsing.py
cs_bahtml/plotting.py
cs_bahtml/transformation.py
cs_bahtml/radars/__init__.py
cs_bahtml-0.1.0.dist-info/AUTHORS.rst
cs_bahtml-0.1.0.dist-info/LICENSE
cs_bahtml-0.1.0.dist-info/METADATA
cs_bahtml-0.1.0.dist-info/WHEEL
cs_bahtml-0.1.0.dist-info/top_level.txt
cs_bahtml-0.1.0.dist-info/RECORD
