Metadata-Version: 2.1
Name: cs_bahtml
Version: 0.1.0
Summary: A util package for ML in CSGO
Home-page: https://github.com/bahtman/cs_bahtml
Author: Anton Baht
Author-email: anton@baht.dk
License: MIT license
Keywords: cs_bahtml
Classifier: Development Status :: 2 - Pre-Alpha
Classifier: Intended Audience :: Developers
Classifier: License :: OSI Approved :: MIT License
Classifier: Natural Language :: English
Classifier: Programming Language :: Python :: 3
Classifier: Programming Language :: Python :: 3.6
Classifier: Programming Language :: Python :: 3.7
Classifier: Programming Language :: Python :: 3.8
Requires-Python: >=3.6
License-File: LICENSE
License-File: AUTHORS.rst
Requires-Dist: geopandas
Requires-Dist: pandas
Requires-Dist: plotly
Requires-Dist: Pillow
Requires-Dist: scikit-learn
